setup.py
cssprefixer/__init__.py
cssprefixer/cssprefixer.py
cssprefixer/rules.py
cssprefixer/test.py
cssprefixer2.egg-info/PKG-INFO
cssprefixer2.egg-info/SOURCES.txt
cssprefixer2.egg-info/dependency_links.txt
cssprefixer2.egg-info/top_level.txt