Metadata-Version: 1.1
Name: cssprefixer2
Version: 1.2
Summary: A tool that rewrites your CSS files, adding vendor-prefixed versions of CSS3 rules.
Home-page: https://github.com/ongspxm/cssprefixer2
Author: Metta Ong
Author-email: ongspxm@gmail.com
License: MIT
Keywords: css3 prefixer
Platform: UNKNOWN
Classifier: Development Status :: 3 - Alpha
Classifier: Topic :: Utilities
Classifier: License :: OSI Approved :: MIT License
Classifier: Intended Audience :: Developers
